chinesedays/__init__.py
chinesedays/__version__.py
chinesedays/date_utils.py
chinesedays/days_base.py
chinesedays/holiday.py
chinesedays/holiday_type.py
chinesedays/data/chinese-days.json
chinese_days-0.0.2.dist-info/METADATA
chinese_days-0.0.2.dist-info/WHEEL
chinese_days-0.0.2.dist-info/licenses/LICENSE
chinese_days-0.0.2.dist-info/RECORD
