Metadata-Version: 2.4
Name: chinese-days
Version: 0.0.2
Summary: Python version of a Chinese holiday, shift change day, and workday lookup library
Project-URL: Homepage, https://github.com/Homalos/chinese-days
Project-URL: Documentation, https://github.com/Homalos/chinese-days/blob/main/README.md
Project-URL: Repository, https://github.com/Homalos/chinese-days
Project-URL: Issues, https://github.com/Homalos/chinese-days/issues
Author-email: Lumosylva <donnymoving@gmail.com>
Maintainer-email: Lumosylva <donnymoving@gmail.com>
License: MIT
License-File: LICENSE
Keywords: calendar,chinese,holiday,holidays,workdays
Classifier: Development Status :: 5 - Production/Stable
Classifier: Intended Audience :: Developers
Classifier: License :: OSI Approved :: MIT License
Classifier: Operating System :: OS Independent
Classifier: Programming Language :: Python :: 3
Classifier: Programming Language :: Python :: 3.10
Classifier: Programming Language :: Python :: 3.11
Classifier: Programming Language :: Python :: 3.12
Classifier: Programming Language :: Python :: 3.13
Classifier: Topic :: Office/Business :: Scheduling
Classifier: Topic :: Software Development :: Libraries :: Python Modules
Requires-Python: >=3.10
Requires-Dist: hatch>=1.14.2
Requires-Dist: twine>=6.2.0
Provides-Extra: dev
Requires-Dist: black>=22.0.0; extra == 'dev'
Requires-Dist: flake8>=5.0.0; extra == 'dev'
Requires-Dist: mypy>=1.0.0; extra == 'dev'
Requires-Dist: pytest-cov>=4.0.0; extra == 'dev'
Requires-Dist: pytest>=7.0.0; extra == 'dev'
